{
  "id": 100,
  "graph": {
    "graph_logic": {
      "conditions": [
        {
          "id": "C_1",
          "type": "文字条件",
          "content": "题目中提到的两个空间：$L^4[0,1]$ 和 $L^2[0,1]$。"
        },
        {
          "id": "C_2",
          "type": "文字条件",
          "content": "$L^4[0,1]$ 是一个包含在 $L^2[0,1]$ 中的函数空间。"
        },
        {
          "id": "C_3",
          "type": "文字条件",
          "content": "$L^2[0,1]$ 是一个包含在 $L^4[0,1]$ 中的函数空间。"
        },
        {
          "id": "C_4",
          "type": "文字条件",
          "content": "题目中的陈述：'Any bounded sequence in $L^4[0,1]$ has a convergent subsequence in $L^2[0,1]$.'"
        },
        {
          "id": "C_5",
          "type": "学科常识",
          "content": "Cauchy-Schwarz 不等式。"
        }
      ],
      "intermediate_steps": [
        {
          "id": "I_1",
          "type": "条件转化",
          "content": "题目陈述的意思是，对于任何在 $L^4[0,1]$ 中的有界序列，它都有一个在 $L^2[0,1]$ 中收敛的子序列。",
          "parents": [
            "C_4"
          ],
          "reasoning_logic": "将英文陈述转化为中文并解释其数学含义。"
        },
        {
          "id": "I_2",
          "type": "逻辑推导",
          "content": "假设有一个在 $L^4[0,1]$ 中的有界序列 $(f_n)$，其中 $f_n$ 在 $L^2[0,1]$ 中不收敛。",
          "parents": [
            "I_1"
          ],
          "reasoning_logic": "为验证陈述，考虑一个反例的假设。"
        },
        {
          "id": "I_3",
          "type": "逻辑推导",
          "content": "对于任意的 $\\epsilon > 0$，存在一个子序列 $(f_{n_k})$，使得 $\\int_0^1 |f_{n_k}(x)|^2 dx > \\epsilon$ 对于所有的 $k$ 都成立。",
          "parents": [
            "I_2"
          ],
          "reasoning_logic": "具体化不收敛的条件。"
        },
        {
          "id": "I_4",
          "type": "逻辑推导",
          "content": "由于 $(f_n)$ 在 $L^4[0,1]$ 中有界，存在一个常数 $M > 0$，使得 $\\int_0^1 |f_n(x)|^4 dx \\leq M$ 对于所有的 $n$ 都成立。",
          "parents": [
            "I_2"
          ],
          "reasoning_logic": "根据有界序列的定义推导出积分上界。"
        },
        {
          "id": "I_5",
          "type": "条件转化",
          "content": "根据 Cauchy-Schwarz 不等式，有 $\\left(\\int_0^1 |f_n(x)|^2 dx\\right)^2 \\leq \\left(\\int_0^1 |f_n(x)|^4 dx\\right) \\left(\\int_0^1 |f_n(x)|^2 dx\\right)$。",
          "parents": [
            "C_5"
          ],
          "reasoning_logic": "引用不等式并应用到序列上。"
        },
        {
          "id": "I_6",
          "type": "数值计算",
          "content": "因此，$\\int_0^1 |f_n(x)|^2 dx \\leq \\frac{M}{\\int_0^1 |f_n(x)|^2 dx} \\cdot \\int_0^1 |f_n(x)|^2 dx = M$。",
          "parents": [
            "I_4",
            "I_5"
          ],
          "reasoning_logic": "从不等式和常数 M 推导出积分上界。"
        },
        {
          "id": "I_7",
          "type": "对比分析",
          "content": "这与之前的假设矛盾，因为 $\\int_0^1 |f_{n_k}(x)|^2 dx > \\epsilon$ 对于所有的 $k$ 都成立。",
          "parents": [
            "I_3",
            "I_6"
          ],
          "reasoning_logic": "比较推导结果与假设条件，发现矛盾。"
        },
        {
          "id": "I_8",
          "type": "综合归纳",
          "content": "因此，这个反例说明了题目中的陈述是错误的。",
          "parents": [
            "I_7"
          ],
          "reasoning_logic": "基于矛盾，归纳出陈述错误。"
        }
      ],
      "final_conclusion": {
        "id": "O",
        "type": "综合归纳",
        "content": "False",
        "parents": [
          "I_8"
        ],
        "reasoning_logic": "综合推理过程得出最终答案。"
      }
    }
  }
}