{
  "id": 108,
  "graph": {
    "graph_logic": {
      "conditions": [
        {
          "id": "C_1",
          "type": "图像信息",
          "content": "图片中显示了北京市的行政区划图，其中标注了“航天育种基地”。"
        },
        {
          "id": "C_2",
          "type": "图像信息",
          "content": "图片中没有提供关于太空种子的具体信息或实验数据。"
        },
        {
          "id": "C_3",
          "type": "文字信息",
          "content": "题目要求分析太空种子提升作物品质后最直接带来的市场层面效应。"
        }
      ],
      "intermediate_steps": [
        {
          "id": "I_1",
          "type": "逻辑推导",
          "content": "航天育种基地位于北京市内。",
          "parents": [
            "C_1"
          ],
          "reasoning_logic": "根据图片中标注的位置信息进行地理定位推导。"
        },
        {
          "id": "I_2",
          "type": "逻辑推导",
          "content": "无法直接从图片中获取太空种子提升作物品质后的市场层面效应。",
          "parents": [
            "C_2"
          ],
          "reasoning_logic": "基于图片缺乏具体数据和信息的现状，得出无法直接提取结论的判断。"
        },
        {
          "id": "I_3",
          "type": "逻辑推导",
          "content": "只能基于已知的事实进行推理来分析市场层面效应。",
          "parents": [
            "C_3",
            "I_2"
          ],
          "reasoning_logic": "结合题目要求和图片信息缺失的情况，确定解题策略为基于事实推理。"
        },
        {
          "id": "I_4",
          "type": "逻辑推导",
          "content": "太空种子提升作物品质后，最直接的市场层面效应是提高农作物的产量和质量。",
          "parents": [
            "I_3"
          ],
          "reasoning_logic": "基于作物品质提升与产量、质量之间的因果逻辑进行推导。"
        },
        {
          "id": "I_5",
          "type": "逻辑推导",
          "content": "提高农作物的产量和质量会增加农民的收入和经济效益。",
          "parents": [
            "I_4"
          ],
          "reasoning_logic": "基于产量质量提升与经济收益之间的逻辑关系进行推导。"
        }
      ],
      "final_conclusion": {
        "id": "O",
        "type": "综合归纳",
        "content": "提高农作物的产量和质量，增加农民的收入和经济效益。",
        "parents": [
          "I_5"
        ],
        "reasoning_logic": "综合前述关于产量、质量及经济影响的推导步骤，得出最终的市场层面效应结论。"
      }
    }
  }
}