{
  "id": 103,
  "graph": {
    "graph_logic": {
      "conditions": [
        {
          "id": "C_1",
          "type": "学科常识",
          "content": "时间无关的薛定谔方程是指薛定谔方程中不包含时间项的方程。"
        },
        {
          "id": "C_2",
          "type": "文字条件",
          "content": "对于一个粒子在势能为零的无限深方形势阱中的运动，其时间无关的薛定谔方程表示为 Hψ = Eψ。"
        },
        {
          "id": "C_3",
          "type": "学科常识",
          "content": "H 是哈密顿算符，ψ是波函数，E 是能量。"
        },
        {
          "id": "C_4",
          "type": "文字条件",
          "content": "在无限深方形势阱中，粒子的波函数形式假设为 ψ(x) = A * sin(kx)。"
        },
        {
          "id": "C_5",
          "type": "学科常识",
          "content": "A 是归一化常数，k 是波数。"
        },
        {
          "id": "C_6",
          "type": "学科常识",
          "content": "哈密顿算符在位置表象下的表达式为 H = -ħ² / (2m) * (d²/dx²) + V(x)。"
        },
        {
          "id": "C_7",
          "type": "文字条件",
          "content": "在无限深方形势阱内部，势能 V(x) = 0。"
        },
        {
          "id": "C_8",
          "type": "学科常识",
          "content": "sin(kx) 的二阶导数为 d²(sin(kx))/dx² = -k² * sin(kx)。"
        },
        {
          "id": "C_9",
          "type": "学科常识",
          "content": "波函数归一化条件为 ∫ |ψ(x)|² dx = 1。"
        },
        {
          "id": "C_10",
          "type": "学科常识",
          "content": "三角恒等式 sin²(θ) = (1 - cos(2θ))/2。"
        }
      ],
      "intermediate_steps": [
        {
          "id": "I_1",
          "type": "条件转化",
          "content": "将 V(x)=0 代入哈密顿算符，得到简化后的方程：-ħ² / (2m) * (d²ψ/dx²) = E * ψ(x)。",
          "parents": [
            "C_2",
            "C_6",
            "C_7"
          ],
          "reasoning_logic": "根据势能条件简化薛定谔方程。"
        },
        {
          "id": "I_2",
          "type": "数值计算",
          "content": "将波函数 ψ(x) = A * sin(kx) 及其二阶导数代入简化方程，得到 -ħ² / (2m) * (-k² * sin(kx)) = E * A * sin(kx)。",
          "parents": [
            "I_1",
            "C_4",
            "C_8"
          ],
          "reasoning_logic": "执行代入操作并应用导数公式。"
        },
        {
          "id": "I_3",
          "type": "逻辑推导",
          "content": "消去非零项 sin(kx) 和常数 A（注：原文逻辑此处有跳跃，直接得出 E 与 k 的关系），推导出能量本征值关系 E = ħ² * k² / (2m)。",
          "parents": [
            "I_2"
          ],
          "reasoning_logic": "对方程两边进行代数化简，消去波函数项。"
        },
        {
          "id": "I_4",
          "type": "条件转化",
          "content": "建立归一化积分方程：A² * ∫ sin²(kx) dx = 1。",
          "parents": [
            "C_9",
            "C_4"
          ],
          "reasoning_logic": "将波函数表达式代入归一化条件。"
        },
        {
          "id": "I_5",
          "type": "数值计算",
          "content": "利用三角恒等式变换被积函数，得到 A² * ∫ (1 - cos(2kx))/2 dx = 1。",
          "parents": [
            "I_4",
            "C_10"
          ],
          "reasoning_logic": "应用三角恒等式展开 sin²(kx)。"
        },
        {
          "id": "I_6",
          "type": "数值计算",
          "content": "计算积分结果并取极限，得出 A² * [∞ - 0] = 1（基于原文逻辑）。",
          "parents": [
            "I_5"
          ],
          "reasoning_logic": "执行积分运算并评估边界条件。"
        },
        {
          "id": "I_7",
          "type": "数值计算",
          "content": "解得 A² = 1，因此归一化常数 A = 1。",
          "parents": [
            "I_6"
          ],
          "reasoning_logic": "求解关于 A 的方程。"
        },
        {
          "id": "I_8",
          "type": "综合归纳",
          "content": "确定最终波函数为 ψ(x) = sin(kx)。",
          "parents": [
            "C_4",
            "I_7"
          ],
          "reasoning_logic": "将求得的 A 值代回波函数表达式。"
        }
      ],
      "final_conclusion": {
        "id": "O",
        "type": "综合归纳",
        "content": "时间无关的薛定谔方程为 Hψ = Eψ，波函数为 ψ(x) = sin(kx)，能量本征值为 E = ħ² * k² / (2m)。",
        "parents": [
          "C_2",
          "I_8",
          "I_3"
        ],
        "reasoning_logic": "综合方程定义、求解出的波函数和能量本征值得出最终陈述。"
      }
    }
  }
}